Metadata-Version: 2.1
Name: CompactTree
Version: 1.0.0
Summary: CompactTree: Lightweight header-only C++ library for loading and traversing trees
Home-page: https://github.com/niemasd/CompactTree
Author: Niema Moshiri
Author-email: niemamoshiri@gmail.com
Keywords: tree phylogenetics fast
Classifier: Development Status :: 3 - Alpha
Classifier: Intended Audience :: Developers
Classifier: Topic :: Software Development :: Build Tools
Classifier: License :: OSI Approved :: GNU General Public License v3 or later (GPLv3+)
Classifier: Programming Language :: Python :: 3
Classifier: Programming Language :: Python :: 3.7
Classifier: Programming Language :: Python :: 3.8
Classifier: Programming Language :: Python :: 3.9
Classifier: Programming Language :: Python :: 3.10
Classifier: Programming Language :: Python :: 3.11
License-File: LICENSE
